odoo/addons/connector/AUTHORS
odoo/addons/connector/CHANGES.rst
odoo/addons/connector/README.rst
odoo/addons/connector/__init__.py
odoo/addons/connector/__manifest__.py
odoo/addons/connector/database.py
odoo/addons/connector/exception.py
odoo/addons/connector/components/__init__.py
odoo/addons/connector/components/backend_adapter.py
odoo/addons/connector/components/binder.py
odoo/addons/connector/components/core.py
odoo/addons/connector/components/listener.py
odoo/addons/connector/components/locker.py
odoo/addons/connector/components/mapper.py
odoo/addons/connector/components/synchronizer.py
odoo/addons/connector/doc/Makefile
odoo/addons/connector/doc/bazaar
odoo/addons/connector/doc/conf.py
odoo/addons/connector/doc/index.rst
odoo/addons/connector/doc/make.bat
odoo/addons/connector/doc/_static/09_datamodel.png
odoo/addons/connector/doc/_static/connector_style.css
odoo/addons/connector/doc/_static/img/LogicSupply_Orange_260x80_transparent.png
odoo/addons/connector/doc/_static/img/akretion_logo.png
odoo/addons/connector/doc/_static/img/c2c_square_baseline_192.jpg
odoo/addons/connector/doc/_static/img/logo-debonix.jpg
odoo/addons/connector/doc/_static/img/magentoerpconnect.png
odoo/addons/connector/doc/_static/img/magentoerpconnect150.png
odoo/addons/connector/doc/_static/img/prestashoperpconnect.png
odoo/addons/connector/doc/_static/img/prestashoperpconnect150.png
odoo/addons/connector/doc/_templates/layout.html
odoo/addons/connector/doc/_templates/navbar.html
odoo/addons/connector/doc/_themes/.gitignore
odoo/addons/connector/doc/api/api_backend.rst
odoo/addons/connector/doc/api/api_channels.rst
odoo/addons/connector/doc/api/api_components.rst
odoo/addons/connector/doc/api/api_event.rst
odoo/addons/connector/doc/api/api_exception.rst
odoo/addons/connector/doc/api/api_queue.rst
odoo/addons/connector/doc/guides/bootstrap_connector.rst
odoo/addons/connector/doc/guides/code_overview.rst
odoo/addons/connector/doc/guides/concepts.rst
odoo11_addon_connector-11.0.1.1.0.dist-info/METADATA
odoo11_addon_connector-11.0.1.1.0.dist-info/WHEEL
odoo11_addon_connector-11.0.1.1.0.dist-info/top_level.txt
odoo11_addon_connector-11.0.1.1.0.dist-info/RECORD
